GrabCarAssignmentdorachua/GrabCarClient.py
GrabCarAssignmentdorachua/MyJSONHelper.py
GrabCarAssignmentdorachua/MySQLManager.py
GrabCarAssignmentdorachua/OurCustomEncoder.py
GrabCarAssignmentdorachua/__init__.py
GrabCarAssignmentdorachua-0.0.8.dist-info/LICENSE
GrabCarAssignmentdorachua-0.0.8.dist-info/METADATA
GrabCarAssignmentdorachua-0.0.8.dist-info/WHEEL
GrabCarAssignmentdorachua-0.0.8.dist-info/top_level.txt
GrabCarAssignmentdorachua-0.0.8.dist-info/RECORD
